MANIFEST.in
README.md
__init__.py
setup.cfg
setup.py
bin/habakkuk
docs/Makefile
docs/conf.py
docs/f2py_install.rst
docs/getting_going.rst
docs/index.rst
docs/introduction.rst
docs/make.bat
src/__init__.py
src/Habakkuk.egg-info/PKG-INFO
src/Habakkuk.egg-info/SOURCES.txt
src/Habakkuk.egg-info/dependency_links.txt
src/Habakkuk.egg-info/requires.txt
src/Habakkuk.egg-info/top_level.txt
src/habakkuk/__init__.py
src/habakkuk/config_ivy_bridge.py
src/habakkuk/dag.py
src/habakkuk/dag_node.py
src/habakkuk/make_dag.py
src/habakkuk/parse2003.py
src/habakkuk/tests/dag_test.py
src/habakkuk/tests/make_dag_test.py
src/habakkuk/tests/parse_test.py
src/habakkuk/tests/sched_test.py
src/habakkuk/tests/test_utilities.py