Metadata-Version: 1.1
Name: Habakkuk
Version: 0.1.0
Summary: Performance prediction for Fortran kernels.
Home-page: https://arporter.github.io/habakkuk/
Author: Andrew R Porter
Author-email: andrew.porter@stfc.ac.uk
License: OSI Approved :: BSD 2-Clause License
Platform: UNKNOWN
Classifier: Development Status :: 3 - Alpha
Classifier: Environment :: Console
Classifier: Programming Language :: Python
Classifier: Programming Language :: Python :: 2.7
Classifier: Topic :: Scientific/Engineering
Classifier: Topic :: Utilities
Classifier: Operating System :: MacOS :: MacOS X
Classifier: Operating System :: POSIX
Classifier: Operating System :: Unix
